fbsa/__init__.py
fbsa/factory.py
fbsa/py.typed
fbsa/pytest.py
fbsa/types.py
factory_boy_sqlalchemy-0.0.2.dist-info/METADATA
factory_boy_sqlalchemy-0.0.2.dist-info/WHEEL
factory_boy_sqlalchemy-0.0.2.dist-info/RECORD
