Metadata-Version: 2.4
Name: factory-boy-sqlalchemy
Version: 0.0.2
Summary: More convinient use of factory boy with sqlalchemy models
Author-email: Damian Świstowski <damian@swistowski.org>
Requires-Python: >=3.12
Requires-Dist: factory-boy<4.0.0,>=3.0.0
Requires-Dist: sqlalchemy<3.0.0,>=2.0.0
